ascii_ye/__init__.py
ascii_ye-0.1.dist-info/METADATA
ascii_ye-0.1.dist-info/WHEEL
ascii_ye-0.1.dist-info/top_level.txt
ascii_ye-0.1.dist-info/RECORD
