Metadata-Version: 2.1
Name: ascii_ye
Version: 0.1
Summary: ASCII_YE ​​is a library that encodes text with the ASCII type, a digital encoding used to encrypt data when making requests over the Internet.
Home-page: https://github.com/mr-sami-x/ascii_ye
Author: SamiSoft - Yemen
Classifier: Programming Language :: Python :: 3
Classifier: License :: OSI Approved :: MIT License
Classifier: Operating System :: OS Independent
Requires-Python: >=3.6
